asclepius/__init__.py
asclepius/auxhilary.py
asclepius/instelling.py
asclepius/medewerker.py
asclepius/parser.py
asclepius/portaaldriver.py
asclepius/regressietest.py
asclepius/releasetest.py
asclepius-0.0.7.dist-info/LICENSE
asclepius-0.0.7.dist-info/METADATA
asclepius-0.0.7.dist-info/WHEEL
asclepius-0.0.7.dist-info/top_level.txt
asclepius-0.0.7.dist-info/RECORD
