Metadata-Version: 2.1
Name: asclepius
Version: 0.0.7
Summary: Python package for ValueCare
Home-page: https://valuecare.nl
Author: ValueCare (Nils Warsen)
Author-email: nils.warsen@valuecare.nl
Classifier: Programming Language :: Python :: 3
Classifier: License :: OSI Approved :: MIT License
Classifier: Operating System :: OS Independent
Requires-Python: >=3.6
License-File: LICENSE
Requires-Dist: pandas
Requires-Dist: selenium
